Workbook

Sheet Monthly Checklist
A1: Law Firm — Finance Department Monthly Checklist
A2: Month: _______________ | Prepared by: _______________ | Date: _______________ | Reviewed by: _______________
A4: # | B4: Category | C4: Sub-Category | D4: Checklist Item | E4: Status | F4: Completed By | G4: Notes | H4: Confirmed By | I4: Status
A5: Billing & Revenue
A6: 1 | B6: Billing & Revenue | C6: Time recording | D6: Confirm all fee earners have submitted time records for the month | E6: Pending | H6: HOD | I6: Pending
A7: 2 | B7: Billing & Revenue | C7: Time recording | D7: Review and approve unbilled time entries; chase outstanding timesheets from fee earners | E7: Pending | H7: HOD | I7: Pending
A8: 3 | B8: Billing & Revenue | C8: Time recording | D8: Identify and write off time entries that will not be recoverable; obtain partner approval | E8: Pending | H8: HOD | I8: Pending
A9: 4 | B9: Billing & Revenue | C9: Time recording | D9: Reconcile total hours recorded to expected billing capacity by fee earner | E9: Pending | H9: HOD | I9: Pending
A10: 5 | B10: Billing & Revenue | C10: Disbursements | D10: Confirm all client disbursements (court fees, counsel fees, searches, stamps) are captured | E10: Pending | H10: HOD | I10: Pending
A11: 6 | B11: Billing & Revenue | C11: Disbursements | D11: Ensure disbursements are correctly coded to client/matter and supported by receipts | E11: Pending | H11: HOD | I11: Pending
A12: 7 | B12: Billing & Revenue | C12: Disbursements | D12: Reconcile disbursements ledger to supporting invoices and receipts | E12: Pending | H12: HOD | I12: Pending
A13: 8 | B13: Billing & Revenue | C13: Invoice generation | D13: Raise all invoices for time and disbursements billed this month | E13: Pending | H13: HOD | I13: Pending
A14: 9 | B14: Billing & Revenue | C14: Invoice generation | D14: Confirm invoices are approved by the responsible partner before dispatch | E14: Pending | H14: HOD | I14: Pending
A15: 10 | B15: Billing & Revenue | C15: Invoice generation | D15: Confirm invoice terms, client reference, and VAT treatment are correct on each invoice | E15: Pending | H15: HOD | I15: Pending
A16: 11 | B16: Billing & Revenue | C16: Invoice generation | D16: Issue invoices to clients and record in the billing register against each matter | E16: Pending | H16: HOD | I16: Pending
A17: 12 | B17: Billing & Revenue | C17: Revenue recognition | D17: Post revenue for invoices raised in the billing ledger | E17: Pending | H17: HOD | I17: Pending
... A19: 14 | B19: Billing & Revenue | C19: Revenue recognition | D19: Reconcile total fees billed vs fees collected vs WIP movement for the month | E19: Pending | H19: HOD | I19: Pending
A20: Client Trust / Ledger Accounts
A21: 15 | B21: Client Trust / Ledger Accounts | C21: Trust reconciliation | D21: Reconcile each client trust/ledger account balance to the trust bank statement | E21: Pending | H21: HOD | I21: Pending
A22: 16 | B22: Client Trust / Ledger Accounts | C22: Trust reconciliation | D22: Confirm aggregate of all individual client ledger balances equals the trust bank balance | E22: Pending | H22: HOD | I22: Pending
A23: 17 | B23: Client Trust / Ledger Accounts | C23: Trust reconciliation | D23: Investigate and resolve any differences in client ledger reconciliations immediately | E23: Pending | H23: HOD | I23: Pending
A24: 18 | B24: Client Trust / Ledger Accounts | C24: Trust compliance | D24: Confirm no client trust funds have been used for office/firm purposes | E24: Pending | H24: HOD | I24: Pending
A25: 19 | B25: Client Trust / Ledger Accounts | C25: Trust compliance | D25: Confirm all client funds received are deposited into the trust account on the same day | E25: Pending | H25: HOD | I25: Pending
A26: 20 | B26: Client Trust / Ledger Accounts | C26: Trust compliance | D26: Review all disbursements from trust; confirm each has client authority and matter reference | E26: Pending | H26: HOD | I26: Pending
A27: 21 | B27: Client Trust / Ledger Accounts | C27: Trust compliance | D27: Confirm trust account does not have a debit balance on any individual client ledger | E27: Pending | H27: HOD | I27: Pending
A28: 22 | B28: Client Trust / Ledger Accounts | C28: Trust compliance | D28: Ensure any interest earned on trust accounts is allocated per policy and regulatory rules | E28: Pending | H28: HOD | I28: Pending
A29: 23 | B29: Client Trust / Ledger Accounts | C29: Matter closure | D29: Identify matters closed this month; confirm all trust funds are returned or applied | E29: Pending | H29: HOD | I29: Pending
A30: 24 | B30: Client Trust / Ledger Accounts | C30: Matter closure | D30: Confirm final bills are raised and any residual trust balances cleared before matter closure | E30: Pending | H30: HOD | I30: Pending
A31: 25 | B31: Client Trust / Ledger Accounts | C31: Matter closure | D31: Archive closed matter financial records per the firm's document retention policy | E31: Pending | H31: HOD
A32: Cash & Bank
A33: 26 | B33: Cash & Bank | C33: Bank reconciliation | D33: Obtain month-end bank statements for all office/firm bank accounts | E33: Pending | H33: HOD | I33: Pending
A34: 27 | B34: Cash & Bank | C34: Bank reconciliation | D34: Reconcile each office bank account closing balance to the general ledger cash book | E34: Pending | H34: HOD | I34: Pending
A35: 28 | B35: Cash & Bank | C35: Bank reconciliation | D35: List all outstanding deposits in transit at month-end; confirm expected clearance dates | E35: Pending | H35: HOD | I35: Pending
A36: 29 | B36: Cash & Bank | C36: Bank reconciliation | D36: List all outstanding cheques and unpresented payments; investigate items over 30 days | E36: Pending | H36: HOD | I36: Pending
A37: 30 | B37: Cash & Bank | C37: Bank reconciliation | D37: Confirm all bank charges, interest, and fees are posted in the cash book | E37: Pending | H37: HOD | I37: Pending
A38: 31 | B38: Cash & Bank | C38: Bank reconciliation | D38: Review bank statement for any unusual or unauthorised transactions; escalate immediately | E38: Pending | H38: HOD | I38: Pending
A39: 32 | B39: Cash & Bank | C39: Bank reconciliation | D39: Confirm no stale cheques (older than 6 months) remain uncleared | E39: Pending | H39: HOD | I39: Pending
A40: 33 | B40: Cash & Bank | C40: Petty cash | D40: Perform physical petty cash count; confirm balance agrees to cashbook | E40: Pending | H40: HOD | I40: Pending
A41: 34 | B41: Cash & Bank | C41: Petty cash | D41: Reconcile petty cash to the petty cash ledger; confirm all vouchers are approved and filed | E41: Pending | H41: HOD | I41: Pending
A42: 35 | B42: Cash & Bank | C42: Petty cash | D42: Replenish petty cash to the approved float level and post replenishment journal | E42: Pending | H42: HOD | I42: Pending
A43: 36 | B43: Cash & Bank | C43: Cash management | D43: Confirm all inter-account transfers are posted in both accounts and reconciled | E43: Pending | H43: HOD | I43: Pending
A44: 37 | B44: Cash & Bank | C44: Cash management | D44: Confirm trust and office bank accounts are clearly segregated in the ledger at all times | E44: Pending | H44: HOD | I44: Pending
... A48: 41 | B48: Cash & Bank | C48: Cash forecasting | D48: Confirm adequate cash is available for next payroll and major payment obligations | E48: Pending | H48: HOD | I48: Pending
A49: Expenditure & Cost Control
A50: 42 | B50: Expenditure & Cost Control | C50: Invoice processing | D50: Confirm all supplier invoices are coded, approved, and posted to the correct cost centre | E50: Pending | H50: HOD | I50: Pending
A51: 43 | B51: Expenditure & Cost Control | C51: Invoice processing | D51: Confirm counsel and expert witness fees are approved and posted against the correct matter | E51: Pending | H51: HOD | I51: Pending
A52: 44 | B52: Expenditure & Cost Control | C52: Accruals & prepayments | D52: Post accruals for costs incurred but not yet invoiced (counsel, searches, utilities) | E52: Pending | H52: HOD | I52: Pending
A53: 45 | B53: Expenditure & Cost Control | C53: Accruals & prepayments | D53: Release prepayments proportionately; confirm remaining balances are valid | E53: Pending | H53: HOD | I53: Pending
A54: 46 | B54: Expenditure & Cost Control | C54: Accruals & prepayments | D54: Accrue office costs — rent, insurance, software licences, library subscriptions | E54: Pending | H54: HOD | I54: Pending
A55: 47 | B55: Expenditure & Cost Control | C55: Cost control | D55: Compare actual costs to budget by department and practice group; flag variances above 10% | E55: Pending | H55: HOD | I55: Pending
A56: 48 | B56: Expenditure & Cost Control | C56: Cost control | D56: Review professional indemnity insurance and other firm insurance costs are correctly posted | E56: Pending | H56: HOD | I56: Pending
A57: 49 | B57: Expenditure & Cost Control | C57: Cost control | D57: Confirm depreciation on office equipment, IT, and leasehold improvements is posted | E57: Pending | H57: HOD | I57: Pending
A58: 50 | B58: Expenditure & Cost Control | C58: Cost control | D58: Review and approve any unbudgeted expenditure above the delegated authority threshold | E58: Pending | H58: HOD | I58: Pending
A59: Advances & Disbursement Float
A60: 51 | B60: Advances & Disbursement Float | C60: Staff advances | D60: Review advances register; confirm all open balances per fee earner and support staff | E60: Pending | H60: HOD | I60: Pending
A61: 52 | B61: Advances & Disbursement Float | C61: Staff advances | D61: Follow up on all advances outstanding beyond the approved clearance period (30 days) | E61: Pending | H61: HOD | I61: Pending
A62: 53 | B62: Advances & Disbursement Float | C62: Staff advances | D62: Post retirement documents for advances liquidated this month | E62: Pending | H62: HOD | I62: Pending
A63: 54 | B63: Advances & Disbursement Float | C63: Staff advances | D63: Confirm no new advance is issued to staff with an unretired prior advance | E63: Pending | H63: HOD | I63: Pending
A64: 55 | B64: Advances & Disbursement Float | C64: Disbursement float | D64: Reconcile disbursement float advances to actual disbursements incurred per matter | E64: Pending | H64: HOD | I64: Pending
A65: 56 | B65: Advances & Disbursement Float | C65: Disbursement float | D65: Confirm client disbursement floats are correctly recorded as client liabilities | E65: Pending | H65: HOD | I65: Pending
A66: 57 | B66: Advances & Disbursement Float | C66: Disbursement float | D66: Follow up on disbursement floats where matters are substantially complete | E66: Pending | H66: HOD | I66: Pending
A67: 58 | B67: Advances & Disbursement Float | C67: Reconciliation | D67: Confirm advances ledger balance agrees to balance sheet advances line | E67: Pending | H67: HOD | I67: Pending
A68: Receivables
A69: 59 | B69: Receivables | C69: Aged analysis | D69: Generate aged receivables report; review all balances by client and matter | E69: Pending | H69: HOD | I69: Pending
A70: 60 | B70: Receivables | C70: Aged analysis | D70: Identify invoices overdue by 30, 60, and 90+ days; escalate 90+ day items to partners | E70: Pending | H70: HOD | I70: Pending
A71: 61 | B71: Receivables | C71: Collections | D71: Issue payment reminders to clients with overdue invoices | E71: Pending | H71: HOD | I71: Pending
A72: 62 | B72: Receivables | C72: Collections | D72: Post all cash receipts; confirm correct allocation to client invoices and matters | E72: Pending | H72: HOD | I72: Pending
A73: 63 | B73: Receivables | C73: Collections | D73: Follow up on disputed fee notes with the responsible partner; document resolution plan | E73: Pending | H73: HOD | I73: Pending
A74: 64 | B74: Receivables | C74: Credit risk | D74: Assess recoverability of aged balances; raise bad debt provision where required | E74: Pending | H74: HOD | I74: Pending
A75: 65 | B75: Receivables | C75: Credit risk | D75: Review credit terms for clients with persistently late payment patterns | E75: Pending | H75: HOD | I75: Pending
A76: 66 | B76: Receivables | C76: Reconciliation | D76: Reconcile receivables ledger total to balance sheet receivables line | E76: Pending | H76: HOD | I76: Pending
A77: Payables
A78: 67 | B78: Payables | C78: Aged analysis | D78: Generate aged payables report; review all balances by supplier | E78: Pending | H78: HOD | I78: Pending
A79: 68 | B79: Payables | C79: Aged analysis | D79: Identify invoices due for payment this month; prepare payment run schedule | E79: Pending | H79: HOD | I79: Pending
A80: 69 | B80: Payables | C80: Payments | D80: Process approved payment run; confirm bank transfers are authorised per policy | E80: Pending | H80: HOD | I80: Pending
A81: 70 | B81: Payables | C81: Payments | D81: Confirm counsel, expert witness, and agent fee payments are made per agreed terms | E81: Pending | H81: HOD | I81: Pending
A82: 71 | B82: Payables | C82: Payments | D82: Reconcile supplier statements to the payables ledger for key vendors | E82: Pending | H82: HOD | I82: Pending
A83: 72 | B83: Payables | C83: Statutory payables | D83: Confirm PAYE, NSSF, NHIF remittances are processed and receipts filed | E83: Pending | H83: HOD | I83: Pending
A84: 73 | B84: Payables | C84: Statutory payables | D84: Confirm VAT payable is correctly calculated on firm fee income | E84: Pending | H84: HOD | I84: Pending
A85: 74 | B85: Payables | C85: Reconciliation | D85: Reconcile payables ledger total to balance sheet payables line | E85: Pending | H85: HOD | I85: Pending
A86: 75 | B86: Payables | C86: Reconciliation | D86: Review long-outstanding creditor balances for continued validity | E86: Pending | H86: HOD | I86: Pending
A87: Payroll & HR Costs
A88: 76 | B88: Payroll & HR Costs | C88: Payroll processing | D88: Confirm approved headcount, new starters, leavers, and salary changes for the month | E88: Pending | H88: HOD | I88: Pending
A89: 77 | B89: Payroll & HR Costs | C89: Payroll processing | D89: Process monthly payroll for partners/directors, fee earners, and support staff | E89: Pending | H89: HOD | I89: Pending
A90: 78 | B90: Payroll & HR Costs | C90: Payroll processing | D90: Reconcile gross pay to approved salary and drawings schedule | E90: Pending | H90: HOD | I90: Pending
A91: 79 | B91: Payroll & HR Costs | C91: Payroll processing | D91: Issue payslips to all staff; confirm net pay agrees to bank transfer total | E91: Pending | H91: HOD | I91: Pending
A92: 80 | B92: Payroll & HR Costs | C92: Statutory deductions | D92: Confirm PAYE, NSSF, NHIF deductions are correctly computed and remitted | E92: Pending | H92: HOD | I92: Pending
A93: 81 | B93: Payroll & HR Costs | C93: Statutory deductions | D93: File statutory remittance returns by due dates and retain receipts | E93: Pending | H93: HOD | I93: Pending
A94: 82 | B94: Payroll & HR Costs | C94: Cost allocation | D94: Allocate payroll costs to practice groups and cost centres | E94: Pending | H94: HOD | I94: Pending
A95: 83 | B95: Payroll & HR Costs | C95: Cost allocation | D95: Post partner drawings and profit distributions per the partnership/shareholder agreement | E95: Pending | H95: HOD | I95: Pending
A96: 84 | B96: Payroll & HR Costs | C96: Cost allocation | D96: Reconcile total payroll cost to the general ledger posting | E96: Pending | H96: HOD | I96: Pending
A97: Tax & Regulatory Compliance
A98: 85 | B98: Tax & Regulatory Compliance | C98: VAT | D98: Reconcile output VAT on fee notes and input VAT on approved supplier invoices | E98: Pending | H98: HOD | I98: Pending
A99: 86 | B99: Tax & Regulatory Compliance | C99: VAT | D99: Prepare and file monthly VAT return by statutory deadline | E99: Pending | H99: HOD | I99: Pending
A100: 87 | B100: Tax & Regulatory Compliance | C100: VAT | D100: Confirm VAT treatment on disbursements — distinguish principal vs agent disbursements | E100: Pending | H100: HOD | I100: Pending
A101: 88 | B101: Tax & Regulatory Compliance | C101: Withholding tax | D101: Confirm withholding tax deducted on advocate/counsel fees and professional payments | E101: Pending | H101: HOD | I101: Pending
A102: 89 | B102: Tax & Regulatory Compliance | C102: Withholding tax | D102: File withholding tax return and remit deducted amounts by due date | E102: Pending | H102: HOD | I102: Pending
A103: 90 | B103: Tax & Regulatory Compliance | C103: Regulatory | D103: Confirm practising certificates and Law Society membership fees are current for all advocates | E103: Pending | H103: HOD | I103: Pending
A104: 91 | B104: Tax & Regulatory Compliance | C104: Regulatory | D104: Review any upcoming LSK, regulatory, or court compliance deadlines | E104: Pending | H104: HOD | I104: Pending
A105: Budget & Management Reporting
...

Sheet Summary
A1: Monthly Checklist — Summary by Section
G3: Confirmed by HOD status
A4: Section | B4: Sub-categories | C4: Total Items | D4: Complete | E4: Pending / Other | F4: Progress | G4: Complete | H4: Pending / Other | I4: Progress
A5: Billing & Revenue | B5: 4 | C5: 14 | D5: =COUNTIF('Monthly Checklist'!E6:E19,"Complete") -> 0 | E5: =14-D5 -> 14 | F5: =IFERROR(D5/C5,0) -> 0 | G5: =COUNTIF('Monthly Checklist'!I6:I19,"Complete") -> 0 | H5: =14-G5 -> 14 | I5: =IFERROR(G5/C5,0) -> 0
A6: Client Trust / Ledger Accounts | B6: 3 | C6: 11 | D6: =COUNTIF('Monthly Checklist'!E21:E31,"Complete") -> 0 | E6: =11-D6 -> 11 | F6: =IFERROR(D6/C6,0) -> 0 | G6: =COUNTIF('Monthly Checklist'!I21:I31,"Complete") -> 0 | H6: =11-G6 -> 11 | I6: =IFERROR(G6/C6,0) -> 0
A7: Cash & Bank | B7: 4 | C7: 16 | D7: =COUNTIF('Monthly Checklist'!E33:E48,"Complete") -> 0 | E7: =16-D7 -> 16 | F7: =IFERROR(D7/C7,0) -> 0 | G7: =COUNTIF('Monthly Checklist'!I33:I48,"Complete") -> 0 | H7: =16-G7 -> 16 | I7: =IFERROR(G7/C7,0) -> 0
A8: Expenditure & Cost Control | B8: 3 | C8: 9 | D8: =COUNTIF('Monthly Checklist'!E50:E58,"Complete") -> 0 | E8: =9-D8 -> 9 | F8: =IFERROR(D8/C8,0) -> 0 | G8: =COUNTIF('Monthly Checklist'!I50:I58,"Complete") -> 0 | H8: =9-G8 -> 9 | I8: =IFERROR(G8/C8,0) -> 0
A9: Advances & Disbursement Float | B9: 3 | C9: 8 | D9: =COUNTIF('Monthly Checklist'!E60:E67,"Complete") -> 0 | E9: =8-D9 -> 8 | F9: =IFERROR(D9/C9,0) -> 0 | G9: =COUNTIF('Monthly Checklist'!I60:I67,"Complete") -> 0 | H9: =8-G9 -> 8 | I9: =IFERROR(G9/C9,0) -> 0
A10: Receivables | B10: 4 | C10: 8 | D10: =COUNTIF('Monthly Checklist'!E69:E76,"Complete") -> 0 | E10: =8-D10 -> 8 | F10: =IFERROR(D10/C10,0) -> 0 | G10: =COUNTIF('Monthly Checklist'!I69:I76,"Complete") -> 0 | H10: =8-G10 -> 8 | I10: =IFERROR(G10/C10,0) -> 0
A11: Payables | B11: 4 | C11: 9 | D11: =COUNTIF('Monthly Checklist'!E78:E86,"Complete") -> 0 | E11: =9-D11 -> 9 | F11: =IFERROR(D11/C11,0) -> 0 | G11: =COUNTIF('Monthly Checklist'!I78:I86,"Complete") -> 0 | H11: =9-G11 -> 9 | I11: =IFERROR(G11/C11,0) -> 0
A12: Payroll & HR Costs | B12: 3 | C12: 9 | D12: =COUNTIF('Monthly Checklist'!E88:E96,"Complete") -> 0 | E12: =9-D12 -> 9 | F12: =IFERROR(D12/C12,0) -> 0 | G12: =COUNTIF('Monthly Checklist'!I88:I96,"Complete") -> 0 | H12: =9-G12 -> 9 | I12: =IFERROR(G12/C12,0) -> 0
A13: Tax & Regulatory Compliance | B13: 3 | C13: 7 | D13: =COUNTIF('Monthly Checklist'!E98:E104,"Complete") -> 0 | E13: =7-D13 -> 7 | F13: =IFERROR(D13/C13,0) -> 0 | G13: =COUNTIF('Monthly Checklist'!I98:I104,"Complete") -> 0 | H13: =7-G13 -> 7 | I13: =IFERROR(G13/C13,0) -> 0
A14: Budget & Management Reporting | B14: 2 | C14: 5 | D14: =COUNTIF('Monthly Checklist'!E106:E110,"Complete") -> 0 | E14: =5-D14 -> 5 | F14: =IFERROR(D14/C14,0) -> 0 | G14: =COUNTIF('Monthly Checklist'!I106:I110,"Complete") -> 0 | H14: =5-G14 -> 5 | I14: =IFERROR(G14/C14,0) -> 0
A15: Governance & Operations | B15: 2 | C15: 6 | D15: =COUNTIF('Monthly Checklist'!E112:E117,"Complete") -> 0 | E15: =6-D15 -> 6 | F15: =IFERROR(D15/C15,0) -> 0 | G15: =COUNTIF('Monthly Checklist'!I112:I117,"Complete") -> 0 | H15: =6-G15 -> 6 | I15: =IFERROR(G15/C15,0) -> 0
A16: TOTAL | B16: 35 | C16: 102 | D16: =SUM(D5:D15) -> 0 | E16: =SUM(E5:E15) -> 102 | F16: =IFERROR(D16/C16,0) -> 0 | G16: =SUM(G5:G15) -> 0 | H16: =SUM(H5:H15) -> 102 | I16: =IFERROR(G16/C16,0) -> 0
