Workbook

Sheet Monthly Checklist
A1: Audit, Accounting & Tax Compliance Firm — Monthly Finance Checklist
A2: Month: _June________ | Prepared by: ___Gregory______ | Date: ___11/7/2026___ | Reviewed by: _______________
A4: # | B4: Category | C4: Sub-Category | D4: Checklist Item | E4: Status | F4: Responsible | G4: Assigned To | H4: Notes | I4: Confirmed by HOD | J4: Status
A5: Billing, Revenue & WIP
A6: 1 | B6: Billing, Revenue & WIP | C6: Timesheet review | D6: Confirm all professional staff have submitted timesheets for every working day of the month | E6: N/A | F6: Accountant | G6: Complete | J6: Pending
A7: 2 | B7: Billing, Revenue & WIP | C7: Timesheet review | D7: Review and approve timesheets; confirm hours are coded to the correct client/engagement | E7: N/A | F7: HOD | G7: Complete | J7: Pending
A8: 3 | B8: Billing, Revenue & WIP | C8: Timesheet review | D8: Identify non-chargeable time (training, admin, BD, leave) and post to correct internal codes | E8: N/A | F8: Accountant | J8: Pending
A9: 4 | B9: Billing, Revenue & WIP | C9: Timesheet review | D9: Reconcile total hours recorded to expected capacity by service line (audit, accounting, tax) | E9: N/A | F9: Accountant | J9: Pending
A10: 5 | B10: Billing, Revenue & WIP | C10: WIP management | D10: Update WIP register for all active audit, accounting, and tax compliance engagements | E10: Complete | F10: Accountant | J10: Pending
A11: 8 | B11: Billing, Revenue & WIP | C11: WIP management | D11: Write down WIP for any engagement where recovery is doubtful; obtain partner approval | E11: Pending | F11: Accountant | J11: Pending
A12: 9 | B12: Billing, Revenue & WIP | C12: Invoice generation | D12: Raise invoices for all completed milestones, monthly retainer fees, and ad hoc work billed this month | E12: Pending | F12: Accountant | J12: Pending
A13: 10 | B13: Billing, Revenue & WIP | C13: Invoice generation | D13: Confirm all invoices are approved by the responsible partner before dispatch to clients | E13: Pending | F13: Accountant | J13: Pending
A14: 11 | B14: Billing, Revenue & WIP | C14: Invoice generation | D14: Confirm invoice amounts, VAT treatment, and client reference agree to the engagement letter | E14: Pending | F14: Accountant | J14: Pending
A15: 12 | B15: Billing, Revenue & WIP | C15: Invoice generation | D15: Issue invoices and record in the billing register against each client and engagement | E15: Pending | F15: Accountant | J15: Pending
A16: 13 | B16: Billing, Revenue & WIP | C16: Revenue recognition | D16: Recognise revenue for work done this month per engagement (% completion or milestone basis) | E16: Pending | F16: Accountant | J16: Pending
A17: 14 | B17: Billing, Revenue & WIP | C17: Revenue recognition | D17: Post deferred income for fees received in advance of work being performed | E17: Pending | F17: Accountant | J17: Pending
A18: 15 | B18: Billing, Revenue & WIP | C18: Revenue recognition | D18: Reconcile recognised revenue to invoices raised and WIP movements for the month | E18: Pending | F18: Accountant | J18: Pending
A19: 16 | B19: Billing, Revenue & WIP | C19: Revenue recognition | D19: Prepare monthly fee income report by service line (audit, accounting, tax compliance) | E19: Pending | F19: Accountant | J19: Pending
A20: Audit Engagements — Monthly Progress
A21: 17 | B21: Audit Engagements — Monthly Progress | C21: Engagement management | D21: Update audit engagement tracker with current status of all active audit assignments | E21: Pending | F21: HOD | J21: Pending
A22: 18 | B22: Audit Engagements — Monthly Progress | C22: Engagement management | D22: Confirm all audit fieldwork scheduled for the month is completed or rescheduled with client agreement | E22: Pending | F22: HOD | J22: Pending
A23: 19 | B23: Audit Engagements — Monthly Progress | C23: Engagement management | D23: Confirm engagement letters are in place for all audits starting this month | E23: Pending | F23: HOD | J23: Pending
A24: 20 | B24: Audit Engagements — Monthly Progress | C24: Engagement management | D24: Confirm audit planning materiality and risk assessments are up to date on active engagements | E24: Pending | F24: Audit Associate | J24: Pending
A25: 21 | B25: Audit Engagements — Monthly Progress | C25: Audit file management | D25: Confirm audit working paper files for all active engagements are being updated and reviewed | E25: Pending | F25: Audit Associate | J25: Pending
A26: 22 | B26: Audit Engagements — Monthly Progress | C26: Audit file management | D26: Confirm all significant audit findings and issues are documented and escalated to partners | E26: Pending | F26: Audit Associate | J26: Pending
A27: 23 | B27: Audit Engagements — Monthly Progress | C27: Audit file management | D27: Confirm outstanding client information requests (PBC lists) are followed up and tracked | E27: Pending | F27: Audit Associate | J27: Pending
A28: 24 | B28: Audit Engagements — Monthly Progress | C28: Audit file management | D28: Confirm all review notes are cleared or carried forward with documented responses | E28: Pending | F28: Audit Associate | J28: Pending
A29: 25 | B29: Audit Engagements — Monthly Progress | C29: Reporting | D29: Confirm all audit reports due for issue this month are completed and issued on time | E29: Pending | F29: Audit Associate | J29: Pending
A30: 26 | B30: Audit Engagements — Monthly Progress | C30: Reporting | D30: Confirm management letters for completed audits are prepared and issued to clients | E30: Pending | F30: Audit Associate | J30: Pending
A31: 27 | B31: Audit Engagements — Monthly Progress | C31: Reporting | D31: Confirm all regulatory submission deadlines (e.g. filing with registrar) for audit clients are met | E31: Pending | F31: Audit Associate | J31: Pending
A32: 28 | B32: Audit Engagements — Monthly Progress | C32: Billing | D32: Confirm audit fee invoices raised match the engagement letter fee schedule or agreed variations | E32: Pending | F32: Audit Associate | J32: Pending
A33: Accounting & Bookkeeping Engagements
A34: 29 | B34: Accounting & Bookkeeping Engagements | C34: Bookkeeping | D34: Confirm all client bookkeeping data (bank statements, invoices, receipts) is received on time | E34: Pending | F34: HOD | J34: Pending
A35: 30 | B35: Accounting & Bookkeeping Engagements | C35: Bookkeeping | D35: Post all client transactions — sales, purchases, payroll, bank — for the month | E35: Pending | F35: Accountant | J35: Pending
A36: 31 | B36: Accounting & Bookkeeping Engagements | C36: Bookkeeping | D36: Reconcile client bank accounts to the cash book for the month | E36: Pending | F36: Accountant | J36: Pending
A37: 32 | B37: Accounting & Bookkeeping Engagements | C37: Bookkeeping | D37: Process client payroll and confirm payroll journals are posted for the month | E37: Pending | F37: Accountant | J37: Pending
A38: 33 | B38: Accounting & Bookkeeping Engagements | C38: Bookkeeping | D38: Confirm all client accounts payable and receivable ledgers are updated and reconciled | E38: Pending | F38: Accountant | J38: Pending
A39: 34 | B39: Accounting & Bookkeeping Engagements | C39: Management accounts | D39: Prepare monthly management accounts for all accounting clients due this month | E39: Pending | F39: HOD | J39: Pending
A40: 35 | B40: Accounting & Bookkeeping Engagements | C40: Management accounts | D40: Confirm management accounts are reviewed by the responsible manager before client delivery | E40: Pending | F40: HOD | J40: Pending
A41: 36 | B41: Accounting & Bookkeeping Engagements | C41: Management accounts | D41: Deliver management accounts to clients within agreed turnaround times | E41: Pending | F41: HOD | J41: Pending
A42: 37 | B42: Accounting & Bookkeeping Engagements | C42: Management accounts | D42: Follow up with clients on any queries arising from management accounts delivered | E42: Pending | F42: HOD | J42: Pending
A43: 38 | B43: Accounting & Bookkeeping Engagements | C43: Reconciliations | D43: Perform month-end reconciliations for all client accounts — bank, debtors, creditors, payroll | E43: Pending | F43: HOD | J43: Pending
A44: 39 | B44: Accounting & Bookkeeping Engagements | C44: Reconciliations | D44: Confirm all client trial balances are in balance and free from unexplained items | E44: Pending | F44: HOD | J44: Pending
A45: 40 | B45: Accounting & Bookkeeping Engagements | C45: Reconciliations | D45: Post month-end journals — accruals, prepayments, depreciation — for all accounting clients | E45: Pending | F45: HOD | J45: Pending
A46: 41 | B46: Accounting & Bookkeeping Engagements | C46: Billing | D46: Confirm accounting/bookkeeping fee invoices raised agree to engagement letter fee schedules | E46: Pending | F46: HOD | J46: Pending
A47: Tax Compliance Engagements
A48: 47 | B48: Tax Compliance Engagements | C48: VAT | D48: Confirm client sales and purchase data is received for VAT computation | E48: Pending | F48: Tax Associate | J48: Pending
A49: 48 | B49: Tax Compliance Engagements | C49: VAT | D49: Confirm VAT computations are prepared, reviewed, and approved before filing | E49: Pending | F49: Tax Associate | J49: Pending
A50: 49 | B50: Tax Compliance Engagements | C50: VAT | D50: Confirm VAT 3 returns are filed on iTax by the 20th for all VAT clients | E50: Pending | F50: HOD | J50: Pending
A51: 50 | B51: Tax Compliance Engagements | C51: VAT | D51: Confirm VAT payment E-slips are generated and shared with clients for payment | E51: Pending | F51: HOD | J51: Pending
A52: 51 | B52: Tax Compliance Engagements | C52: Withholding Tax | D52: Confirm WHT schedules are prepared for all applicable client payments this month | E52: Pending | F52: HOD | J52: Pending
A53: 52 | B53: Tax Compliance Engagements | C53: Withholding Tax | D53: Confirm WHT returns are filed on iTax by the 20th for all WHT clients | E53: Pending | F53: HOD | J53: Pending
A54: 53 | B54: Tax Compliance Engagements | C54: Withholding Tax | D54: Confirm WHT certificates are generated and distributed to suppliers on behalf of clients | E54: Pending | F54: HOD | J54: Pending
A55: 54 | B55: Tax Compliance Engagements | C55: Compliance tracker | D55: Update tax compliance tracker with filing status for each client and obligation | E55: Pending | F55: HOD | J55: Pending
A56: 55 | B56: Tax Compliance Engagements | C56: Compliance tracker | D56: Flag any overdue filings or pending payments; escalate to engagement manager | E56: Pending | F56: HOD | J56: Pending
A57: 56 | B57: Tax Compliance Engagements | C57: Billing | D57: Confirm tax compliance fee invoices raised agree to engagement letter fee schedules | E57: Pending | F57: HOD | J57: Pending
A58: Cash & Bank
A59: 57 | B59: Cash & Bank | C59: Bank reconciliation | D59: Obtain month-end bank statements for all firm bank accounts | E59: Pending | F59: Accountant | J59: Pending
A60: 58 | B60: Cash & Bank | C60: Bank reconciliation | D60: Reconcile each firm bank account closing balance to the general ledger cash book | E60: Pending | F60: Accountant | J60: Pending
A61: 59 | B61: Cash & Bank | C61: Bank reconciliation | D61: List all outstanding deposits in transit at month-end; confirm expected clearance dates | E61: Pending | F61: HOD | J61: Pending
A62: 60 | B62: Cash & Bank | C62: Bank reconciliation | D62: List all outstanding cheques and unpresented payments; investigate items over 30 days | E62: Pending | F62: HOD | J62: Pending
A63: 61 | B63: Cash & Bank | C63: Bank reconciliation | D63: Confirm all bank charges, interest, and fees are posted in the firm cash book | E63: Pending | F63: HOD | J63: Pending
A64: 62 | B64: Cash & Bank | C64: Bank reconciliation | D64: Review bank statement for unusual or unauthorised transactions; escalate immediately | E64: Pending | F64: HOD | J64: Pending
A65: 63 | B65: Cash & Bank | C65: Bank reconciliation | D65: Confirm no stale cheques (older than 6 months) remain uncleared on the reconciliation | E65: Pending | F65: HOD | J65: Pending
A66: 64 | B66: Cash & Bank | C66: Petty cash | D66: Perform physical petty cash count; confirm balance agrees to the cashbook | E66: Pending | F66: HOD | J66: Pending
A67: 65 | B67: Cash & Bank | C67: Petty cash | D67: Reconcile petty cash to the petty cash ledger; confirm all vouchers are approved and filed | E67: Pending | F67: HOD | J67: Pending
A68: 66 | B68: Cash & Bank | C68: Petty cash | D68: Replenish petty cash to the approved float level and post replenishment journal | E68: Pending | F68: HOD | J68: Pending
A69: 67 | B69: Cash & Bank | C69: Cash management | D69: Confirm all inter-bank transfers are posted in both accounts and reconciled | E69: Pending | F69: HOD | J69: Pending
A70: 68 | B70: Cash & Bank | C70: Cash management | D70: Review month-end cash position against minimum operating balance requirements | E70: Pending | F70: HOD | J70: Pending
... A74: 72 | B74: Cash & Bank | C74: Cash forecasting | D74: Confirm adequate cash is available for next payroll run and major payment obligations | E74: Pending | F74: HOD | J74: Pending
A75: Advances
A76: 73 | B76: Advances | C76: Staff advances | D76: Review advances register; confirm all open balances per staff member | E76: Pending | F76: HOD | J76: Pending
A77: 74 | B77: Advances | C77: Staff advances | D77: Follow up on all advances outstanding beyond the approved clearance period (30 days) | E77: Pending | F77: HOD | J77: Pending
A78: 75 | B78: Advances | C78: Staff advances | D78: Post retirement documents for advances liquidated this month | E78: Pending | F78: HOD | J78: Pending
A79: 76 | B79: Advances | C79: Staff advances | D79: Confirm no new advance is issued to staff with an unretired prior advance | E79: Pending | F79: HOD | J79: Pending
A80: 77 | B80: Advances | C80: Client disbursements | D80: Reconcile any out-of-pocket client disbursements to approved engagement budgets | E80: Pending | F80: Accountant | J80: Pending
A81: 78 | B81: Advances | C81: Client disbursements | D81: Confirm all client disbursements are invoiced and recoverable per engagement letter | E81: Pending | F81: HOD | J81: Pending
A82: 79 | B82: Advances | C82: Client disbursements | D82: Confirm firm funds advanced for client disbursements are correctly recorded as receivables | E82: Pending | F82: HOD | J82: Pending
A83: 80 | B83: Advances | C83: Reconciliation | D83: Confirm advances ledger balance agrees to balance sheet advances line | E83: Pending | F83: HOD | J83: Pending
A84: Receivables
A85: 81 | B85: Receivables | C85: Aged analysis | D85: Generate aged receivables report; review all balances by client and engagement | E85: Pending | F85: HOD | J85: Pending
A86: 82 | B86: Receivables | C86: Aged analysis | D86: Identify invoices overdue by 30, 60, and 90+ days; escalate 90+ day items to partners | E86: Pending | F86: HOD | J86: Pending
A87: 83 | B87: Receivables | C87: Collections | D87: Issue payment reminders to clients with overdue invoices | E87: Pending | F87: HOD | J87: Pending
A88: 84 | B88: Receivables | C88: Collections | D88: Post all cash receipts; confirm correct allocation to client invoices and engagements | E88: Pending | F88: Accountant | J88: Pending
A89: 85 | B89: Receivables | C89: Collections | D89: Follow up on disputed fee notes with the responsible partner; document resolution plan | E89: Pending | F89: Accountant | J89: Pending
A90: 86 | B90: Receivables | C90: Credit risk | D90: Assess recoverability of aged balances; raise bad debt provision where required | E90: Pending | F90: Accountant | J90: Pending
A91: 87 | B91: Receivables | C91: Credit risk | D91: Review credit terms for clients with persistently late payment patterns | E91: Pending | F91: Accountant | J91: Pending
A92: 88 | B92: Receivables | C92: Reconciliation | D92: Reconcile receivables ledger total to balance sheet receivables line | E92: Pending | F92: Accountant | J92: Pending
A93: Payables
A94: 89 | B94: Payables | C94: Aged analysis | D94: Generate aged payables report; review all balances by supplier | E94: Pending | F94: Accountant | J94: Pending
A95: 90 | B95: Payables | C95: Aged analysis | D95: Identify invoices due for payment this month; prepare payment run schedule | E95: Pending | F95: Accountant | J95: Pending
A96: 91 | B96: Payables | C96: Payments | D96: Process approved payment run; confirm bank transfers are authorised per policy | E96: Pending | F96: Accountant | J96: Pending
A97: 92 | B97: Payables | C97: Payments | D97: Confirm specialist sub-contractor and expert fee payments are made per agreed terms | E97: Pending | F97: Accountant | J97: Pending
A98: 93 | B98: Payables | C98: Payments | D98: Reconcile supplier statements to the payables ledger for key vendors | E98: Pending | F98: Accountant | J98: Pending
A99: 94 | B99: Payables | C99: Statutory payables | D99: Confirm firm PAYE, NSSF, NHIF remittances are processed and receipts are filed | E99: Pending | F99: Accountant | J99: Pending
A100: 95 | B100: Payables | C100: Statutory payables | D100: Confirm firm VAT and WHT obligations are met and receipts are retained | E100: Pending | F100: Accountant | J100: Pending
A101: 96 | B101: Payables | C101: Reconciliation | D101: Reconcile payables ledger total to balance sheet payables line | E101: Pending | F101: Accountant | J101: Pending
A102: 97 | B102: Payables | C102: Reconciliation | D102: Review long-outstanding creditor balances for continued validity | E102: Pending | F102: Accountant | J102: Pending
A103: Payroll & Staff Costs
A104: 98 | B104: Payroll & Staff Costs | C104: Payroll processing | D104: Confirm approved headcount, new starters, leavers, and salary changes for the month | E104: Pending | F104: Accountant | J104: Pending
...

Sheet Summary
A1: Monthly Checklist — Summary by Section
G3: Confirmed by HOD status
A4: Section | B4: Sub-categories | C4: Total Items | D4: Complete | E4: Pending / Other | F4: Progress | G4: Complete | H4: Pending / Other | I4: Progress
A5: Billing, Revenue & WIP | B5: 4 | C5: 16 | D5: =COUNTIF('Monthly Checklist'!E6:E19,"Complete") -> 1 | E5: =16-D5 -> 15 | F5: =IFERROR(D5/C5,0) -> 0.0625 | G5: =COUNTIF('Monthly Checklist'!J6:J19,"Complete") -> 0 | H5: =16-G5 -> 16 | I5: =IFERROR(G5/B5,0) -> 0
A6: Audit Engagements — Monthly Progress | B6: 4 | C6: 12 | D6: =COUNTIF('Monthly Checklist'!E21:E32,"Complete") -> 0 | E6: =12-D6 -> 12 | F6: =IFERROR(D6/C6,0) -> 0 | G6: =COUNTIF('Monthly Checklist'!J21:J32,"Complete") -> 0 | H6: =12-G6 -> 12 | I6: =IFERROR(G6/B6,0) -> 0
A7: Accounting & Bookkeeping Engagements | B7: 4 | C7: 13 | D7: =COUNTIF('Monthly Checklist'!E34:E46,"Complete") -> 0 | E7: =13-D7 -> 13 | F7: =IFERROR(D7/C7,0) -> 0 | G7: =COUNTIF('Monthly Checklist'!J34:J46,"Complete") -> 0 | H7: =13-G7 -> 13 | I7: =IFERROR(G7/B7,0) -> 0
A8: Tax Compliance Engagements | B8: 6 | C8: 15 | D8: =COUNTIF('Monthly Checklist'!E48:E57,"Complete") -> 0 | E8: =15-D8 -> 15 | F8: =IFERROR(D8/C8,0) -> 0 | G8: =COUNTIF('Monthly Checklist'!J48:J57,"Complete") -> 0 | H8: =15-G8 -> 15 | I8: =IFERROR(G8/B8,0) -> 0
A9: Cash & Bank | B9: 4 | C9: 16 | D9: =COUNTIF('Monthly Checklist'!E59:E74,"Complete") -> 0 | E9: =16-D9 -> 16 | F9: =IFERROR(D9/C9,0) -> 0 | G9: =COUNTIF('Monthly Checklist'!J59:J74,"Complete") -> 0 | H9: =16-G9 -> 16 | I9: =IFERROR(G9/B9,0) -> 0
A10: Advances | B10: 3 | C10: 8 | D10: =COUNTIF('Monthly Checklist'!E76:E83,"Complete") -> 0 | E10: =8-D10 -> 8 | F10: =IFERROR(D10/C10,0) -> 0 | G10: =COUNTIF('Monthly Checklist'!J76:J83,"Complete") -> 0 | H10: =8-G10 -> 8 | I10: =IFERROR(G10/B10,0) -> 0
A11: Receivables | B11: 4 | C11: 8 | D11: =COUNTIF('Monthly Checklist'!E85:E92,"Complete") -> 0 | E11: =8-D11 -> 8 | F11: =IFERROR(D11/C11,0) -> 0 | G11: =COUNTIF('Monthly Checklist'!J85:J92,"Complete") -> 0 | H11: =8-G11 -> 8 | I11: =IFERROR(G11/B11,0) -> 0
A12: Payables | B12: 4 | C12: 9 | D12: =COUNTIF('Monthly Checklist'!E94:E102,"Complete") -> 0 | E12: =9-D12 -> 9 | F12: =IFERROR(D12/C12,0) -> 0 | G12: =COUNTIF('Monthly Checklist'!J94:J102,"Complete") -> 0 | H12: =9-G12 -> 9 | I12: =IFERROR(G12/B12,0) -> 0
A13: Payroll & Staff Costs | B13: 3 | C13: 9 | D13: =COUNTIF('Monthly Checklist'!E104:E112,"Complete") -> 0 | E13: =9-D13 -> 9 | F13: =IFERROR(D13/C13,0) -> 0 | G13: =COUNTIF('Monthly Checklist'!J104:JH112,"Complete") -> 0 | H13: =9-G13 -> 9 | I13: =IFERROR(G13/B13,0) -> 0
A14: Lock-up, Utilisation & Engagement Profitability | B14: 3 | C14: 8 | D14: =COUNTIF('Monthly Checklist'!E114:E121,"Complete") -> 0 | E14: =8-D14 -> 8 | F14: =IFERROR(D14/C14,0) -> 0 | G14: =COUNTIF('Monthly Checklist'!J114:J121,"Complete") -> 0 | H14: =8-G14 -> 8 | I14: =IFERROR(G14/B14,0) -> 0
A15: Quality Control & Professional Compliance | B15: 4 | C15: 9 | D15: =COUNTIF('Monthly Checklist'!E123:E131,"Complete") -> 0 | E15: =9-D15 -> 9 | F15: =IFERROR(D15/C15,0) -> 0 | G15: =COUNTIF('Monthly Checklist'!J123:J131,"Complete") -> 0 | H15: =9-G15 -> 9 | I15: =IFERROR(G15/B15,0) -> 0
A16: Management Reporting & Governance | B16: 2 | C16: 8 | D16: =COUNTIF('Monthly Checklist'!E133:E140,"Complete") -> 0 | E16: =8-D16 -> 8 | F16: =IFERROR(D16/C16,0) -> 0 | G16: =COUNTIF('Monthly Checklist'!J133:J140,"Complete") -> 0 | H16: =8-G16 -> 8 | I16: =IFERROR(G16/B16,0) -> 0
A17: TOTAL | B17: =SUM(B5:B16) -> 45 | C17: =SUM(C5:C16) -> 131 | D17: =SUM(D5:D16) -> 1 | E17: =SUM(E5:E16) -> 130 | F17: =AVERAGE(F8:F16) -> 0 | G17: =SUM(G5:G16) -> 0 | H17: =SUM(H5:H16) -> 131 | I17: =AVERAGE(I5:I16) -> 0
